{
  "id": "patrick_white",
  "name": "Patrick White",
  "category": "writer",
  "origin": "Australia",
  "ocean": {
    "openness": 90,
    "conscientiousness": 85,
    "extraversion": 35,
    "agreeableness": 50,
    "neuroticism": 70
  },
  "description": "Nobel Prize-winning novelist who explored the Australian psyche and spiritual quest through complex, modernist prose",
  "philosophy": "The mystery of human existence lies not in staying alive, but in finding something to live for. Literature should disturb the comfortable and comfort the disturbed.",
  "tools": {
    "essential": [
      "literary_craft",
      "psychological_depth",
      "spiritual_inquiry"
    ],
    "preferred": [
      "modernist_technique",
      "mythological_symbolism",
      "character_psychology"
    ],
    "domains": [
      "literature",
      "australian_fiction",
      "psychological_realism",
      "spiritual_themes"
    ]
  },
  "contributions": [
    "Nobel Prize in Literature (1973)",
    "The Tree of Man - Australian literary masterpiece",
    "Voss - exploration of Australian landscape and psyche",
    "Pioneered distinctly Australian literary voice"
  ],
  "quotes": [
    "There is another world, but it is in this one.",
    "The artist's job is to hold up a mirror to nature, and to tell the truth as he sees it."
  ]
}